activelearner/__init__.py
activelearner-0.1.0.dist-info/LICENCE.txt
activelearner-0.1.0.dist-info/METADATA
activelearner-0.1.0.dist-info/WHEEL
activelearner-0.1.0.dist-info/top_level.txt
activelearner-0.1.0.dist-info/RECORD
