Metadata-Version: 2.1
Name: activelearner
Version: 0.1.0
Summary: This is a library to use Active Learning in Text Classification and Topic Modeling.
Home-page: https://github.com/ArshadSameemdeen/Text-Classification-Topic-Modeling-Active-Learner
Author: Arshad Sameemdeen
Author-email: arshadsameemdeen@gmail.com
License: MIT
Keywords: active learning
Platform: UNKNOWN
Classifier: Development Status :: 5 - Production/Stable
Classifier: Intended Audience :: Education
Classifier: Operating System :: Microsoft :: Windows :: Windows 10
Classifier: License :: OSI Approved :: MIT License
Classifier: Programming Language :: Python :: 3
